{
  "title": "Git repo based customizations",
  "description": "Install customizations from a git repository",
  "handler": "handlers/repo.js",
  "buildOrder": 10,
  "modules": {
    "animatedfox.json": {
      "description": "AnimatedFox Theme"
    },
    "ff-ultima.json": {
      "description": "Completely customizable firefox theme"
    },
    "firefox-ui-fix.json": {
      "description": "Firefox UI fix"
    },
    "materialfox.json": {
      "description": "MaterialFox Theme"
    },
    "minifox.json": {
      "description": "Minifox Theme"
    },
    "safari-style.json": {
      "description": "Safari Style"
    },
    "uwp.json": {
      "description": "UWP (windows) Theme"
    },
    "wavefox.json": {
      "description": "WaveFox Theme"
    }
  }
}
